MANIFEST.in
README.rst
setup.py
SapphireQuant/__init__.py
SapphireQuant/setup_pyc.py
SapphireQuant.egg-info/PKG-INFO
SapphireQuant.egg-info/SOURCES.txt
SapphireQuant.egg-info/dependency_links.txt
SapphireQuant.egg-info/requires.txt
SapphireQuant.egg-info/top_level.txt
SapphireQuant/Channel/__init__.py
SapphireQuant/Channel/CtpChannel/CtpConvert.py
SapphireQuant/Channel/CtpChannel/CtpQuoteChannel.py
SapphireQuant/Channel/CtpChannel/CtpTest.py
SapphireQuant/Channel/CtpChannel/CtpTradeChannel.py
SapphireQuant/Channel/CtpChannel/__init__.py
SapphireQuant/Channel/CtpChannel/_thostmduserapi.pyd
SapphireQuant/Channel/CtpChannel/_thosttraderapi.pyd
SapphireQuant/Channel/CtpChannel/thostmduserapi.py
SapphireQuant/Channel/CtpChannel/thostmduserapi_se.dll
SapphireQuant/Channel/CtpChannel/thosttraderapi.py
SapphireQuant/Channel/CtpChannel/thosttraderapi_se.dll
SapphireQuant/Config/__init__.py
SapphireQuant/Config/Account/PhysicalAccount.py
SapphireQuant/Config/Account/__init__.py
SapphireQuant/Config/Ctp/CtpBroker.py
SapphireQuant/Config/Ctp/CtpBrokerCollection.py
SapphireQuant/Config/Ctp/CtpBrokerManager.py
SapphireQuant/Config/Ctp/CtpCounter.py
SapphireQuant/Config/Ctp/CtpCounterGroup.py
SapphireQuant/Config/Ctp/CtpServer.py
SapphireQuant/Config/Ctp/EnumNetworkType.py
SapphireQuant/Config/Ctp/EnumServerType.py
SapphireQuant/Config/Ctp/__init__.py
SapphireQuant/Config/Instrument/FutureManager.py
SapphireQuant/Config/Instrument/InstrumentManager.py
SapphireQuant/Config/Instrument/__init__.py
SapphireQuant/Config/TradingDay/HolidayHelper.py
SapphireQuant/Config/TradingDay/TradingDayHelper.py
SapphireQuant/Config/TradingDay/__init__.py
SapphireQuant/Config/TradingFrame/FutureExchangeTradingFrame.py
SapphireQuant/Config/TradingFrame/FutureProductTradingFrame.py
SapphireQuant/Config/TradingFrame/FutureTradingFrame.py
SapphireQuant/Config/TradingFrame/FutureTradingTime.py
SapphireQuant/Config/TradingFrame/LimitValue.py
SapphireQuant/Config/TradingFrame/TradingFrameHelper.py
SapphireQuant/Config/TradingFrame/TradingFrameManager.py
SapphireQuant/Config/TradingFrame/TradingFrameNode.py
SapphireQuant/Config/TradingFrame/__init__.py
SapphireQuant/Core/Bar.py
