Metadata-Version: 2.1
Name: SapphireQuant
Version: 1.3.4
Summary: Python Quantitative Investment@2021
Home-page: https://github.com/CarlSnow/SapphireQuant
Author: CarlSnow
Author-email: carl.snow.china@gmail.com
Maintainer: CarlSnow
Maintainer-email: carl.snow.china@gmail.com
License: Apache License
Platform: all
Classifier: Development Status :: 4 - Beta
Classifier: Operating System :: OS Independent
Classifier: Intended Audience :: Developers
Classifier: License :: OSI Approved :: BSD License
Classifier: Programming Language :: Python
Classifier: Programming Language :: Python :: Implementation
Classifier: Programming Language :: Python :: 3.5
Classifier: Programming Language :: Python :: 3.6
Classifier: Programming Language :: Python :: 3.7
Classifier: Programming Language :: Python :: 3.8
Classifier: Topic :: Software Development :: Libraries
